niwrap_mrtrix3tissue/mrtrix3tissue/__init__.py
niwrap_mrtrix3tissue/mrtrix3tissue/ss3t_csd_beta1.py
niwrap_mrtrix3tissue-0.8.3.dist-info/WHEEL
niwrap_mrtrix3tissue-0.8.3.dist-info/METADATA
niwrap_mrtrix3tissue-0.8.3.dist-info/RECORD
